dataco/__init__.py
dataco/__version__.py
dataco/cloud_service.py
dataco-0.1.2.dist-info/LICENSE
dataco-0.1.2.dist-info/METADATA
dataco-0.1.2.dist-info/WHEEL
dataco-0.1.2.dist-info/top_level.txt
dataco-0.1.2.dist-info/RECORD
