Metadata-Version: 2.1
Name: dataco
Version: 0.1.2
Summary: tool to interact with data from different storage services
Home-page: https://github.com/sang-d/data-connector
Author: SangDinh
Author-email: sxuan29@gmail.com
Requires-Python: >=3.4, <4
License-File: LICENSE
Requires-Dist: pandas
Requires-Dist: boto3
Requires-Dist: google-api-python-client
Requires-Dist: google-auth-httplib2
Requires-Dist: google-auth-oauthlib
